iiitb_SISO_Shiftregister.v
module dff(d,clk,q);
    input d,clk;
    output q;
    reg q=0;
    always @ (posedge clk)
    begin
    q<=d;
end
endmodule 

module siso(d, clk, q);
    input d,clk;
    output q;
    wire q1,q2,q3;
    dff a(d, clk, q1);
    dff b(q1, clk, q2);
    dff c(q2, clk, q3);
    dff d1(q3, clk, q);
endmodule

iiitb_SISO_Shiftregister_tb.v
module testbench();
reg d,clk;
wire q;
siso a(d, clk, q);
initial
begin
$monitor($time,"d=%b,clk=%b,q=%b",d,clk,q);
end
initial
begin
$dumpfile("test1.vcd");
$dumpvars(0,testbench);
clk=1'b0;
forever #5 clk=~clk;
end
initial
begin
d=1;
#10 d=0;
#10 d=1;
#10 d=1;
#40 $finish;
end 
endmodule

test1.vcd
$date
	Wed Aug 10 22:41:14 2022
$end
$version
	Icarus Verilog
$end
$timescale
	1s
$end
$scope module testbench $end
$var wire 1 ! q $end
$var reg 1 " clk $end
$var reg 1 # d $end
$scope module a $end
$var wire 1 " clk $end
$var wire 1 # d $end
$var wire 1 $ q3 $end
$var wire 1 % q2 $end
$var wire 1 & q1 $end
$var wire 1 ! q $end
$scope module a $end
$var wire 1 " clk $end
$var wire 1 # d $end
$var reg 1 & q $end
$upscope $end
$scope module b $end
$var wire 1 " clk $end
$var wire 1 & d $end
$var reg 1 % q $end
$upscope $end
$scope module c $end
$var wire 1 " clk $end
$var wire 1 % d $end
$var reg 1 $ q $end
$upscope $end
$scope module d1 $end
$var wire 1 " clk $end
$var wire 1 $ d $end
$var reg 1 ! q $end
$upscope $end
$upscope $end
$upscope $end
$enddefinitions $end
#0
$dumpvars
0&
0%
0$
1#
0"
0!
$end
#5
1&
1"
#10
0"
0#
#15
1%
0&
1"
#20
0"
1#
#25
1&
0%
1$
1"
#30
0"
#35
1!
0$
1%
1"
#40
0"
#45
1$
0!
1"
#50
0"
#55
1!
1"
